CHANGELOG.md
LICENSE.txt
MANIFEST.in
README.md
requirements.txt
setup.cfg
setup.py
useintest/__init__.py
useintest/common.py
useintest.egg-info/PKG-INFO
useintest.egg-info/SOURCES.txt
useintest.egg-info/dependency_links.txt
useintest.egg-info/requires.txt
useintest.egg-info/top_level.txt
useintest/executables/__init__.py
useintest/executables/builders.py
useintest/executables/common.py
useintest/executables/controllers.py
useintest/executables/models.py
useintest/executables/paths_to_mount.py
useintest/modules/__init__.py
useintest/modules/bissell/__init__.py
useintest/modules/bissell/bissell.py
useintest/modules/consul/__init__.py
useintest/modules/consul/consul.py
useintest/modules/couchdb/__init__.py
useintest/modules/couchdb/couchdb.py
useintest/modules/gitlab/__init__.py
useintest/modules/gitlab/gitlab.py
useintest/modules/gitlab/helpers.py
useintest/modules/gogs/__init__.py
useintest/modules/gogs/gogs.py
useintest/modules/irods/__init__.py
useintest/modules/irods/executables.py
useintest/modules/irods/helpers.py
useintest/modules/irods/models.py
useintest/modules/irods/services.py
useintest/modules/irods/setup_irods.py
useintest/modules/mongo/__init__.py
useintest/modules/mongo/mongo.py
useintest/modules/samtools/__init__.py
useintest/modules/samtools/samtools.py
useintest/services/__init__.py
useintest/services/builders.py
useintest/services/controllers.py
useintest/services/exceptions.py
useintest/services/models.py
useintest/tests/__init__.py
useintest/tests/common.py
useintest/tests/executables/__init__.py
useintest/tests/executables/common.py
useintest/tests/executables/test_controllers.py
useintest/tests/modules/__init__.py
useintest/tests/modules/bissell/__init__.py
useintest/tests/modules/bissell/test_bissell.py
useintest/tests/modules/consul/__init__.py
useintest/tests/modules/consul/test_consul.py
useintest/tests/modules/couchdb/__init__.py
useintest/tests/modules/couchdb/test_couchdb.py
useintest/tests/modules/gitlab/__init__.py
useintest/tests/modules/gitlab/test_gitlab.py
useintest/tests/modules/gitlab/test_helpers.py
useintest/tests/modules/gogs/__init__.py
useintest/tests/modules/gogs/test_gogs.py
