Metadata-Version: 1.1
Name: useintest
Version: 5.0.0
Summary: I don't care how it's done, I just want to use it in my tests!
Home-page: https://github.com/wtsi-hgi/useintest
Author: Colin Nolan
Author-email: colin.nolan@sanger.ac.uk
License: MIT
Platform: UNKNOWN
Classifier: Development Status :: 5 - Production/Stable
Classifier: Operating System :: OS Independent
Classifier: Programming Language :: Python :: 3.6
Classifier: License :: OSI Approved :: MIT License
